[
  {
    "meta": {
      "symbol": "JPM",
      "generated_at": "2026-02-23T08:42:39Z",
      "mode": "simulation"
    },
    "market": {
      "current_price": 310.7900085449219,
      "predicted_price_next_session": 309.0033495630095
    },
    "signals": {
      "trend_label": "WEAK DOWNTREND ",
      "sentiment_score": 0.0,
      "check_engine_light": " YELLOW (Neutral / Noise)"
    },
    "evidence": {
      "headlines_used": [
        "JPM announces date for shareholder meeting",
        "Market volatility continues ahead of Fed decision"
      ]
    }
  },
  {
    "meta": {
      "symbol": "JPM",
      "source_symbol": "JPM",
      "generated_at": "2026-03-03T16:41:07Z",
      "market_session_date": "2026-03-03",
      "mode": "simulation"
    },
    "market": {
      "current_price": 297.0,
      "predicted_price_next_session": 299.11917104642157,
      "history": [
        {
          "time": "2025-12-05",
          "value": 313.6253356933594
        },
        {
          "time": "2025-12-08",
          "value": 313.7945556640625
        },
        {
          "time": "2025-12-09",
          "value": 299.16058349609375
        },
        {
          "time": "2025-12-10",
          "value": 308.7174377441406
        },
        {
          "time": "2025-12-11",
          "value": 315.9548034667969
        },
        {
          "time": "2025-12-12",
          "value": 317.0896911621094
        },
        {
          "time": "2025-12-15",
          "value": 318.58294677734375
        },
        {
          "time": "2025-12-16",
          "value": 314.1330261230469
        },
        {
          "time": "2025-12-17",
          "value": 313.5655822753906
        },
        {
          "time": "2025-12-18",
          "value": 311.594482421875
        },
        {
          "time": "2025-12-19",
          "value": 315.7855529785156
        },
        {
          "time": "2025-12-22",
          "value": 321.63916015625
        },
        {
          "time": "2025-12-23",
          "value": 324.4664001464844
        },
        {
          "time": "2025-12-24",
          "value": 327.6918640136719
        },
        {
          "time": "2025-12-26",
          "value": 326.4375305175781
        },
        {
          "time": "2025-12-29",
          "value": 322.29620361328125
        },
        {
          "time": "2025-12-30",
          "value": 321.96771240234375
        },
        {
          "time": "2025-12-31",
          "value": 320.7730712890625
        },
        {
          "time": "2026-01-02",
          "value": 324.0184326171875
        },
        {
          "time": "2026-01-05",
          "value": 332.5400085449219
        },
        {
          "time": "2026-01-06",
          "value": 334.6099853515625
        },
        {
          "time": "2026-01-07",
          "value": 326.989990234375
        },
        {
          "time": "2026-01-08",
          "value": 329.7900085449219
        },
        {
          "time": "2026-01-09",
          "value": 329.19000244140625
        },
        {
          "time": "2026-01-12",
          "value": 324.489990234375
        },
        {
          "time": "2026-01-13",
          "value": 310.8999938964844
        },
        {
          "time": "2026-01-14",
          "value": 307.8699951171875
        },
        {
          "time": "2026-01-15",
          "value": 309.260009765625
        },
        {
          "time": "2026-01-16",
          "value": 312.4700012207031
        },
        {
          "time": "2026-01-20",
          "value": 302.739990234375
        },
        {
          "time": "2026-01-21",
          "value": 302.0400085449219
        },
        {
          "time": "2026-01-22",
          "value": 303.6300048828125
        },
        {
          "time": "2026-01-23",
          "value": 297.7200012207031
        },
        {
          "time": "2026-01-26",
          "value": 301.0400085449219
        },
        {
          "time": "2026-01-27",
          "value": 300.30999755859375
        },
        {
          "time": "2026-01-28",
          "value": 300.7699890136719
        },
        {
          "time": "2026-01-29",
          "value": 306.4200134277344
        },
        {
          "time": "2026-01-30",
          "value": 305.8900146484375
        },
        {
          "time": "2026-02-02",
          "value": 308.1400146484375
        },
        {
          "time": "2026-02-03",
          "value": 314.8500061035156
        },
        {
          "time": "2026-02-04",
          "value": 317.2699890136719
        },
        {
          "time": "2026-02-05",
          "value": 310.1600036621094
        },
        {
          "time": "2026-02-06",
          "value": 322.3999938964844
        },
        {
          "time": "2026-02-09",
          "value": 322.1000061035156
        },
        {
          "time": "2026-02-10",
          "value": 318.2799987792969
        },
        {
          "time": "2026-02-11",
          "value": 310.82000732421875
        },
        {
          "time": "2026-02-12",
          "value": 302.6400146484375
        },
        {
          "time": "2026-02-13",
          "value": 302.54998779296875
        },
        {
          "time": "2026-02-17",
          "value": 307.1300048828125
        },
        {
          "time": "2026-02-18",
          "value": 308.7799987792969
        },
        {
          "time": "2026-02-19",
          "value": 308.04998779296875
        },
        {
          "time": "2026-02-20",
          "value": 310.7900085449219
        },
        {
          "time": "2026-02-23",
          "value": 297.6700134277344
        },
        {
          "time": "2026-02-24",
          "value": 297.29998779296875
        },
        {
          "time": "2026-02-25",
          "value": 303.29998779296875
        },
        {
          "time": "2026-02-26",
          "value": 306.1300048828125
        },
        {
          "time": "2026-02-27",
          "value": 300.29998779296875
        },
        {
          "time": "2026-03-02",
          "value": 297.55999755859375
        },
        {
          "time": "2026-03-03",
          "value": 297.0
        }
      ]
    },
    "signals": {
      "trend_label": "STRONG DOWNTREND ",
      "sentiment_score": 0.13282285928726195,
      "check_engine_light": " RED (Risk Detected - Caution)"
    },
    "evidence": {
      "headlines_used": [
        "Why Investors Never Seem To Earn the \u2018Average\u2019 Market Return",
        "JPMorgan CEO Jamie Dimon Slams Stablecoin Yield Demands: 'The Public Will Pay'",
        "JPMorgan revamps Nvidia stock price target for rest of 2026",
        "JPMorgan CEO Jaime Dimon: Inflation \u2018Skunk at the Party\u2019 Could Be Back",
        "3 Clear Winners When Exploring High-Yield Savings Accounts"
      ],
      "chart_path": "data\\charts\\2026-03-04\\JPM_trend.png"
    }
  }
]