[
  {
    "meta": {
      "symbol": "MSFT",
      "generated_at": "2026-02-09T03:39:29Z",
      "mode": "simulation"
    },
    "market": {
      "current_price": 401.1400146484375,
      "predicted_price_next_session": 418.23432490907874
    },
    "signals": {
      "trend_label": "STRONG DOWNTREND ",
      "sentiment_score": 0.0,
      "check_engine_light": " RED (Risk Detected - Caution)"
    },
    "evidence": {
      "headlines_used": [
        "MSFT announces date for shareholder meeting",
        "Market volatility continues ahead of Fed decision"
      ]
    }
  },
  {
    "meta": {
      "symbol": "MSFT",
      "generated_at": "2026-02-11T01:55:25Z",
      "mode": "simulation"
    },
    "market": {
      "current_price": 413.2699890136719,
      "predicted_price_next_session": 410.72756389749463
    },
    "signals": {
      "trend_label": "STRONG DOWNTREND ",
      "sentiment_score": 0.0,
      "check_engine_light": " RED (Risk Detected - Caution)"
    },
    "evidence": {
      "headlines_used": [
        "MSFT announces date for shareholder meeting",
        "Market volatility continues ahead of Fed decision"
      ]
    }
  },
  {
    "meta": {
      "symbol": "MSFT",
      "generated_at": "2026-02-11T02:24:15Z",
      "mode": "simulation"
    },
    "market": {
      "current_price": 413.2699890136719,
      "predicted_price_next_session": 402.12090194204586
    },
    "signals": {
      "trend_label": "WEAK DOWNTREND ",
      "sentiment_score": 0.0,
      "check_engine_light": " YELLOW (Neutral / Noise)"
    },
    "evidence": {
      "headlines_used": [
        "MSFT announces date for shareholder meeting",
        "Market volatility continues ahead of Fed decision"
      ]
    }
  },
  {
    "meta": {
      "symbol": "MSFT",
      "generated_at": "2026-02-12T13:23:05Z",
      "mode": "simulation"
    },
    "market": {
      "current_price": 404.3699951171875,
      "predicted_price_next_session": 393.94253479247425
    },
    "signals": {
      "trend_label": "STRONG DOWNTREND ",
      "sentiment_score": 0.0,
      "check_engine_light": " RED (Risk Detected - Caution)"
    },
    "evidence": {
      "headlines_used": [
        "MSFT announces date for shareholder meeting",
        "Market volatility continues ahead of Fed decision"
      ]
    }
  },
  {
    "meta": {
      "symbol": "MSFT",
      "generated_at": "2026-02-12T13:25:20Z",
      "mode": "simulation"
    },
    "market": {
      "current_price": 404.3699951171875,
      "predicted_price_next_session": 393.94253479247425
    },
    "signals": {
      "trend_label": "STRONG DOWNTREND ",
      "sentiment_score": 0.0,
      "check_engine_light": " RED (Risk Detected - Caution)"
    },
    "evidence": {
      "headlines_used": [
        "MSFT announces date for shareholder meeting",
        "Market volatility continues ahead of Fed decision"
      ]
    }
  },
  {
    "meta": {
      "symbol": "MSFT",
      "generated_at": "2026-02-27T02:43:20Z",
      "mode": "simulation"
    },
    "market": {
      "current_price": 401.7200012207031,
      "predicted_price_next_session": 393.1060175078982
    },
    "signals": {
      "trend_label": "STRONG DOWNTREND ",
      "sentiment_score": -0.5697961688041687,
      "check_engine_light": " RED (Risk Detected - Caution)"
    },
    "evidence": {
      "headlines_used": [
        "Nvidia stock falls as Q4 beat, guidance fail to satisfy Wall Street",
        "Trump lays out a new ground rule for Big Tech's AI build-out: Bring your own power",
        "1 Clear Signal to Buy Microsoft Stock",
        "Block lays off nearly half its staff because of AI. Its CEO said most companies will do the same",
        "Citrini Scare Marked the Bottom, Says Fund Betting on Bounce"
      ]
    }
  },
  {
    "meta": {
      "symbol": "MSFT",
      "generated_at": "2026-02-27T11:36:58Z",
      "market_session_date": "2026-02-26",
      "mode": "simulation"
    },
    "market": {
      "current_price": 401.7200012207031,
      "predicted_price_next_session": 393.1060175078982
    },
    "signals": {
      "trend_label": "STRONG DOWNTREND ",
      "sentiment_score": -0.38712135553359983,
      "check_engine_light": " RED (Risk Detected - Caution)"
    },
    "evidence": {
      "headlines_used": [
        "Nvidia stock falls as Q4 beat, guidance fail to satisfy Wall Street",
        "Nvidia Looks Like a Value Stock Even as Earnings Scream Growth",
        "CoreWeave Stock Drops. It Posted Mixed Earnings and a Whole Lot of Debt.",
        "Magnet Wars: How the U.S. Plans to Break China\u2019s Grip on Rare Earths",
        "Wartsila CEO eyes boost from Trump datacenter push"
      ],
      "chart_path": "data\\charts\\2026-02-27\\MSFT_trend.png"
    }
  }
]